source/__init__.py
source/app.py
source/sam_rules/AWS_Serverless_Api.json
source/sam_rules/AWS_Serverless_Application.json
source/sam_rules/AWS_Serverless_Connector.json
source/sam_rules/AWS_Serverless_Function.json
source/sam_rules/AWS_Serverless_GraphQLApi.json
source/sam_rules/AWS_Serverless_HttpApi.json
source/sam_rules/AWS_Serverless_LayerVersion.json
source/sam_rules/AWS_Serverless_SimpleTable.json
source/sam_rules/AWS_Serverless_StateMachine.json
cfn2iam-0.1.5.dist-info/METADATA
cfn2iam-0.1.5.dist-info/WHEEL
cfn2iam-0.1.5.dist-info/entry_points.txt
cfn2iam-0.1.5.dist-info/licenses/LICENSE
cfn2iam-0.1.5.dist-info/RECORD
