Metadata-Version: 2.4
Name: cfn2iam
Version: 0.1.5
Summary: A tool to automatically generate minimal IAM policy to deploy a CloudFormation stack from its template.
Project-URL: Homepage, https://github.com/mrlikl/cfn2iam.git
Author-email: S Murali Krishnan <mrlikrsh@gmail.com>
License-File: LICENSE
Keywords: aws,cloudformation,iam,permissions
Classifier: License :: OSI Approved :: MIT License
Classifier: Operating System :: OS Independent
Classifier: Programming Language :: Python :: 3
Classifier: Topic :: Utilities
Requires-Python: >=3.9
Requires-Dist: pyyaml>=6.0.3
Requires-Dist: typer>=0.21.1
Provides-Extra: iam
Requires-Dist: boto3>=1.26; extra == 'iam'
